caps_lock_indicator/__init__.py
caps_lock_indicator-0.1.0.dist-info/METADATA
caps_lock_indicator-0.1.0.dist-info/WHEEL
caps_lock_indicator-0.1.0.dist-info/RECORD
